estimium/__init__.py
estimium/base.py
estimium-0.2.0.dist-info/LICENSE
estimium-0.2.0.dist-info/WHEEL
estimium-0.2.0.dist-info/METADATA
estimium-0.2.0.dist-info/RECORD
