Metadata-Version: 2.1
Name: estimium
Version: 0.2.0
Summary: A collection of ML tools written with professor's chalk
License: MIT
Author: Mateusz Zakrzewski
Author-email: mrtovsky@protonmail.com
Requires-Python: >=3.7,<4.0
Classifier: Framework :: Flake8
Classifier: License :: OSI Approved :: MIT License
Classifier: Programming Language :: Python :: 3
Classifier: Programming Language :: Python :: 3.7
Classifier: Programming Language :: Python :: 3.8
Classifier: Topic :: Software Development :: Libraries :: Python Modules
